migra/__init__.py
migra/changes.py
migra/command.py
migra/migra.py
migra/statements.py
migra/util.py
migra-3.0.1652017683.dist-info/entry_points.txt
migra-3.0.1652017683.dist-info/LICENSE
migra-3.0.1652017683.dist-info/WHEEL
migra-3.0.1652017683.dist-info/METADATA
migra-3.0.1652017683.dist-info/RECORD
