Metadata-Version: 2.1
Name: migra
Version: 3.0.1652017683
Summary: Like `diff` but for PostgreSQL schemas
Home-page: https://databaseci.com/docs/migra
License: Unlicense
Author: Robert Lechte
Author-email: robertlechte@gmail.com
Requires-Python: >=3.7,<4
Classifier: License :: Other/Proprietary License
Classifier: Programming Language :: Python :: 3
Classifier: Programming Language :: Python :: 3.10
Classifier: Programming Language :: Python :: 3.7
Classifier: Programming Language :: Python :: 3.8
Classifier: Programming Language :: Python :: 3.9
Provides-Extra: pg
Requires-Dist: psycopg2-binary; extra == "pg"
Requires-Dist: schemainspect (>=3.1.1652015119)
Requires-Dist: six
Requires-Dist: sqlbag
Project-URL: Repository, https://github.com/djrobstep/migra
